f9columnar/__init__.py
f9columnar/arrays.py
f9columnar/data/PMGxsecDB_mc16.txt
f9columnar/data/PMGxsecDB_mc21.txt
f9columnar/data/campaigns.json
f9columnar/data/luminosity.json
f9columnar/data/periods.json
f9columnar/data/truth_classification.json
f9columnar/dataset_builder.py
f9columnar/hdf5_dataloader.py
f9columnar/hdf5_writer.py
f9columnar/histograms.py
f9columnar/ml/__init__.py
f9columnar/ml/dataloader_helpers.py
f9columnar/ml/dataset_scaling.py
f9columnar/ml/hdf5_dataloader.py
f9columnar/ml/hdf5_parallel_writer.py
f9columnar/ml/hdf5_writer.py
f9columnar/ml/imbalanced_sampler.py
f9columnar/ml/lightning_data_module.py
f9columnar/ml/scalers.py
f9columnar/processors.py
f9columnar/processors_collection.py
f9columnar/root_dataloader.py
f9columnar/run.py
f9columnar/submit/__init__.py
f9columnar/submit/act_driver.py
f9columnar/submit/act_handler.py
f9columnar/submit/act_merger.py
f9columnar/submit/act_run.py
f9columnar/submit/act_run.sh
f9columnar/utils/__init__.py
f9columnar/utils/ak_helpers.py
f9columnar/utils/config_utils.py
f9columnar/utils/helpers.py
f9columnar/utils/loggers.py
f9columnar/utils/regex_helpers.py
f9columnar/utils/rucio_db.py
f9columnar/utils/rucio_utils.py
f9columnar/utils/xsec_db.py
f9columnar-0.3.14.dist-info/METADATA
f9columnar-0.3.14.dist-info/WHEEL
f9columnar-0.3.14.dist-info/licenses/LICENSE
f9columnar-0.3.14.dist-info/RECORD
