Metadata-Version: 2.4
Name: f9columnar
Version: 0.3.14
Summary: Columnar analysis utils.
License: MIT
License-File: LICENSE
Author: Jan Gavranovic
Author-email: jan.gavranovic@cern.ch
Requires-Python: >=3.10,<3.13
Classifier: License :: OSI Approved :: MIT License
Classifier: Programming Language :: Python :: 3
Classifier: Programming Language :: Python :: 3.10
Classifier: Programming Language :: Python :: 3.11
Classifier: Programming Language :: Python :: 3.12
Provides-Extra: torch
Requires-Dist: awkward (>=2.6.7,<3.0.0)
Requires-Dist: corner (>=2.2.2,<3.0.0)
Requires-Dist: h5py (>=3.11.0,<4.0.0)
Requires-Dist: hist[plot] (>=2.7.3,<3.0.0)
Requires-Dist: imbalanced-learn (>=0.13.0,<0.14.0)
Requires-Dist: matplotlib (>=3.9.2,<4.0.0)
Requires-Dist: mplhep (>=0.3.50,<0.4.0)
Requires-Dist: networkx (>=3.3,<4.0)
Requires-Dist: numba (>=0.60.0,<0.61.0)
Requires-Dist: numpy (>=2.0.2,<3.0.0)
Requires-Dist: pandas (>=2.2.2,<3.0.0)
Requires-Dist: plothist (>=1.2.6,<2.0.0)
Requires-Dist: psutil (>=6.1.0,<7.0.0)
Requires-Dist: pydot (>=3.0.1,<4.0.0)
Requires-Dist: requests (>=2.28.1,<3.0.0)
Requires-Dist: rich (>=13.7.0,<14.0.0)
Requires-Dist: scikit-learn (>=1.6.1,<2.0.0)
Requires-Dist: scipy (>=1.14.1,<2.0.0)
Requires-Dist: seaborn (>=0.13.2,<0.14.0)
Requires-Dist: sympy (>=1.13.1,<2.0.0)
Requires-Dist: tables (>=3.10.1,<4.0.0)
Requires-Dist: torch (==2.8.0) ; extra == "torch"
Requires-Dist: tqdm (>=4.65.0,<5.0.0)
Requires-Dist: uncertainties (>=3.2.2,<4.0.0)
Requires-Dist: uproot (>=5.3.10,<6.0.0)
Requires-Dist: vector (>=1.4.1,<2.0.0)
Project-URL: Repository, https://gitlab.cern.ch/ijs-f9-ljubljana/f9columnar
